red_warden/__engines/engines.py
red_warden/__graphql/__datazones/graphql/datapath/connections.py
red_warden/__graphql/__datazones/graphql/datapath/mutations.py
red_warden/__graphql/__datazones/graphql/datapath/types.py
red_warden/__graphql/__datazones/graphql/key/connections.py
red_warden/__graphql/__datazones/graphql/key/mutations.py
red_warden/__graphql/__datazones/graphql/key/types.py
red_warden/__graphql/__datazones/graphql/tenant/connections.py
red_warden/__graphql/__datazones/graphql/tenant/mutations.py
red_warden/__graphql/__datazones/graphql/tenant/types.py
red_warden/__graphql/__datazones/rw_manager/graphql.py
red_warden/__graphql/graphql.py
red_warden/__init__.py
red_warden/auth.py
red_warden/config.py
red_warden/datalayer.py
red_warden/datazones/RWManager/__init__.py
red_warden/datazones/RWManager/controllers.py
red_warden/datazones/RWManager/logic.py
red_warden/datazones/RWManager/migrations/000001.py
red_warden/datazones/RWManager/models.py
red_warden/enums.py
red_warden/helpers.py
red_warden/i18n.py
red_warden/mvc.py
red_warden/oauth2.py
red_warden/responses.py
red_warden/routing.py
red_warden/sessions.py
red_warden-0.4.4.dist-info/LICENSE
red_warden-0.4.4.dist-info/WHEEL
red_warden-0.4.4.dist-info/METADATA
red_warden-0.4.4.dist-info/RECORD
