Metadata-Version: 2.1
Name: red-warden
Version: 0.4.4
Summary: Resilient, Extensible and Distributed Web Application Rapid Development ENgine
Author: Daniele 'px' Picca (Sevenia)
Author-email: d.picca@sevenia.tech
Requires-Python: >=3.8,<4.0
Classifier: Programming Language :: Python :: 3
Classifier: Programming Language :: Python :: 3.8
Classifier: Programming Language :: Python :: 3.9
Requires-Dist: Mako (>=1.1.4,<2.0.0)
Requires-Dist: SQLAlchemy (<1.4)
Requires-Dist: aioauth (>=1.0.3,<2.0.0)
Requires-Dist: aioredis (>=1.3.1,<2.0.0)
Requires-Dist: cryptography (>=3.4.7,<4.0.0)
Requires-Dist: databases[mysql] (>=0.4.3,<0.5.0)
Requires-Dist: gunicorn (>=20.1.0,<21.0.0)
Requires-Dist: httpx (>=0.18.1,<0.19.0)
Requires-Dist: motor (>=2.4.0,<3.0.0)
Requires-Dist: pydantic[email] (>=1.8.2,<2.0.0)
Requires-Dist: pyotp (>=2.6.0,<3.0.0)
Requires-Dist: starlette[full] (>=0.14.2,<0.15.0)
Requires-Dist: uvicorn[standard] (>=0.13.4,<0.14.0)
